LbDiracWrappers/__init__.py
LbDiracWrappers-1.3.1.dist-info/LICENSE
LbDiracWrappers-1.3.1.dist-info/METADATA
LbDiracWrappers-1.3.1.dist-info/WHEEL
LbDiracWrappers-1.3.1.dist-info/entry_points.txt
LbDiracWrappers-1.3.1.dist-info/top_level.txt
LbDiracWrappers-1.3.1.dist-info/RECORD
